meldedaten_faker.py
app/__init__.py
app/__main__.py
app/application.py
meldedaten_faker-0.5.0.dist-info/LICENSE
meldedaten_faker-0.5.0.dist-info/METADATA
meldedaten_faker-0.5.0.dist-info/WHEEL
meldedaten_faker-0.5.0.dist-info/entry_points.txt
meldedaten_faker-0.5.0.dist-info/top_level.txt
meldedaten_faker-0.5.0.dist-info/RECORD
