Metadata-Version: 2.1
Name: meldedaten-faker
Version: 0.5.0
Summary: Generates fake citizen registration data
Home-page: UNKNOWN
Author: Dominik Visca
Author-email: dominik.visca@hs-mainz.de
License: MIT
Platform: UNKNOWN
Requires-Python: >=3.9
License-File: LICENSE
Requires-Dist: click (>=7.1.2)
Requires-Dist: faker (>=9.2.0)
Requires-Dist: overpy (>=0.6)
Requires-Dist: pandas (>=1.3.3)
Requires-Dist: geojson (>=2.5.0)
